snakevonmats/__init__.py
snakevonmats/snake.py
snakegamebymats-0.0.4.dist-info/LICENSE
snakegamebymats-0.0.4.dist-info/METADATA
snakegamebymats-0.0.4.dist-info/WHEEL
snakegamebymats-0.0.4.dist-info/top_level.txt
snakegamebymats-0.0.4.dist-info/RECORD
