Metadata-Version: 2.1
Name: snakegamebymats
Version: 0.0.4
Summary: Einfaches Snake Spiel
Author: Mats Adel
Author-email: matsadel11@gmail.com
Classifier: Programming Language :: Python :: 3
Classifier: License :: OSI Approved :: MIT License
Classifier: Operating System :: OS Independent
Requires-Python: >=3.6
License-File: LICENSE
